khipu/__init__.py
khipu/analysis.py
khipu/command_line.py
khipu/epdsConstructor.py
khipu/extended.py
khipu/formula_filter.py
khipu/isotopes.py
khipu/main.py
khipu/model.py
khipu/plot.py
khipu/test.py
khipu/tree_formulas.py
khipu/utils.py
khipu_metabolomics-2.0.4.dist-info/licenses/LICENSE
khipu_metabolomics-2.0.4.dist-info/METADATA
khipu_metabolomics-2.0.4.dist-info/WHEEL
khipu_metabolomics-2.0.4.dist-info/entry_points.txt
khipu_metabolomics-2.0.4.dist-info/top_level.txt
khipu_metabolomics-2.0.4.dist-info/RECORD
