Metadata-Version: 2.4
Name: khipu-metabolomics
Version: 2.0.4
Summary: Common utilities for interpreting mass spectrometry data
Home-page: https://github.com/shuzhao-li/khipu
Author: Shuzhao Li
Author-email: shuzhao.li@gmail.com
License: BSD
Keywords: chemistry,bioinformatics,mass spectrometry
Classifier: Development Status :: 4 - Beta
Classifier: Intended Audience :: Developers
Classifier: Intended Audience :: Science/Research
Classifier: License :: OSI Approved :: BSD License
Classifier: Natural Language :: English
Classifier: Operating System :: OS Independent
Classifier: Programming Language :: Python :: 3.7
Classifier: Topic :: Scientific/Engineering :: Bio-Informatics
Classifier: Topic :: Software Development :: Libraries :: Python Modules
Requires-Python: >=3.7
License-File: LICENSE
Requires-Dist: intervaltree
Requires-Dist: isocor
Requires-Dist: mass2chem
Requires-Dist: matplotlib
Requires-Dist: numpy
Requires-Dist: networkx
Requires-Dist: pandas
Requires-Dist: requests
Requires-Dist: scipy
Requires-Dist: treelib
Dynamic: author
Dynamic: author-email
Dynamic: classifier
Dynamic: description
Dynamic: description-content-type
Dynamic: home-page
Dynamic: keywords
Dynamic: license
Dynamic: license-file
Dynamic: requires-dist
Dynamic: requires-python
Dynamic: summary
